{
  "summary_section_found": true,
  "total_units": 260,
  "total_actual_rent": 263419.0,
  "average_rent": 1013.15,
  "occupancy_rate": 0.927,
  "total_market_rent": 291166.0,
  "total_square_feet": 221092.0,
  "status_breakdown": [
    {
      "status": "Occupied",
      "count": 241
    },
    {
      "status": "Vacant",
      "count": 19
    }
  ],
  "charge_codes": [
    {
      "charge_type": "appliance_rent",
      "total_amount": 175.0
    },
    {
      "charge_type": "base_rent",
      "total_amount": 198320.0
    },
    {
      "charge_type": "garage_rent",
      "total_amount": 1365.0
    },
    {
      "charge_type": "housing_authority_program_split_ledger",
      "total_amount": 60744.0
    },
    {
      "charge_type": "month_to_month_fees",
      "total_amount": 1300.0
    },
    {
      "charge_type": "parking",
      "total_amount": 1145.0
    },
    {
      "charge_type": "pet_fees",
      "total_amount": 20.0
    },
    {
      "charge_type": "pet_rent",
      "total_amount": 350.0
    }
  ]
}